Workbook

Sheet sales
A1: Sale ID | B1: Date | C1: Commune | D1: Seller | E1: Product | F1: Quantity | G1: Unit price | H1: Revenue | I1: Total Revenue
A2: S083 | B2: 46266 | C2: Plateau | D2: Mariam | E2: Savon | F2: 6 | G2: =_xlfn.XLOOKUP(E2, products!$A$2:$A$7, products!$C$2:$C$7) -> 400 | H2: =F2*G2 -> 2400 | I2: =SUM(H2:H181) -> 2154900
A3: S171 | B3: 46266 | C3: Marcory | D3: Mariam | E3: Savon | F3: 1 | G3: =_xlfn.XLOOKUP(E3, products!$A$2:$A$7, products!$C$2:$C$7) -> 400 | H3: =F3*G3 -> 400
A4: S025 | B4: 46267 | C4: Yopougon | D4: Koffi | E4: Savon | F4: 10 | G4: =_xlfn.XLOOKUP(E4, products!$A$2:$A$7, products!$C$2:$C$7) -> 400 | H4: =F4*G4 -> 4000
A5: S046 | B5: 46267 | C5: Plateau | D5: Mariam | E5: Attiéké 1kg | F5: 5 | G5: =_xlfn.XLOOKUP(E5, products!$A$2:$A$7, products!$C$2:$C$7) -> 700 | H5: =F5*G5 -> 3500
A6: S142 | B6: 46267 | C6: Cocody | D6: Awa | E6: Attiéké 1kg | F6: 4 | G6: =_xlfn.XLOOKUP(E6, products!$A$2:$A$7, products!$C$2:$C$7) -> 700 | H6: =F6*G6 -> 2800
A7: S036 | B7: 46268 | C7: Abobo | D7: Mariam | E7: Huile 1L | F7: 12 | G7: =_xlfn.XLOOKUP(E7, products!$A$2:$A$7, products!$C$2:$C$7) -> 1800 | H7: =F7*G7 -> 21600
A8: S047 | B8: 46268 | C8: Cocody | D8: Awa | E8: Savon | F8: 2 | G8: =_xlfn.XLOOKUP(E8, products!$A$2:$A$7, products!$C$2:$C$7) -> 400 | H8: =F8*G8 -> 800
A9: S079 | B9: 46268 | C9: Yopougon | D9: Koffi | E9: Sucre 1kg | F9: 6 | G9: =_xlfn.XLOOKUP(E9, products!$A$2:$A$7, products!$C$2:$C$7) -> 1000 | H9: =F9*G9 -> 6000
A10: S088 | B10: 46268 | C10: Plateau | D10: Mariam | E10: Lait en poudre 400g | F10: 7 | G10: =_xlfn.XLOOKUP(E10, products!$A$2:$A$7, products!$C$2:$C$7) -> 3200 | H10: =F10*G10 -> 22400
A11: S129 | B11: 46268 | C11: Yopougon | D11: Koffi | E11: Savon | F11: 8 | G11: =_xlfn.XLOOKUP(E11, products!$A$2:$A$7, products!$C$2:$C$7) -> 400 | H11: =F11*G11 -> 3200
A12: S157 | B12: 46269 | C12: Abobo | D12: Mariam | E12: Riz 5kg | F12: 4 | G12: =_xlfn.XLOOKUP(E12, products!$A$2:$A$7, products!$C$2:$C$7) -> 4500 | H12: =F12*G12 -> 18000
A13: S049 | B13: 46270 | C13: Plateau | D13: Mariam | E13: Attiéké 1kg | F13: 1 | G13: =_xlfn.XLOOKUP(E13, products!$A$2:$A$7, products!$C$2:$C$7) -> 700 | H13: =F13*G13 -> 700
A14: S011 | B14: 46271 | C14: Plateau | D14: Mariam | E14: Savon | F14: 9 | G14: =_xlfn.XLOOKUP(E14, products!$A$2:$A$7, products!$C$2:$C$7) -> 400 | H14: =F14*G14 -> 3600
... A181: S112 | B181: 46321 | C181: Abobo | D181: Koffi | E181: Lait en poudre 400g | F181: 4 | G181: =_xlfn.XLOOKUP(E181, products!$A$2:$A$7, products!$C$2:$C$7) -> 3200 | H181: =F181*G181 -> 12800

Sheet products
A1: Product | B1: Category | C1: Unit price (FCFA) | D1: Unit cost (FCFA)
A2: Riz 5kg | B2: Cereals | C2: 4500 | D2: 3600
A3: Huile 1L | B3: Oils | C3: 1800 | D3: 1400
A4: Sucre 1kg | B4: Sugar | C4: 1000 | D4: 800
A5: Savon | B5: Hygiene | C5: 400 | D5: 250
A6: Lait en poudre 400g | B6: Dairy | C6: 3200 | D6: 2600
A7: Attiéké 1kg | B7: Cereals | C7: 700 | D7: 450

Sheet summary
A1: Commune | B1: Revenue | D1: Seller | E1: Sales | F1: Average sale
A2: Cocody | B2: =SUMIFS(sales!$H$2:$H$181, sales!$C$2:$C$181, A2) -> 424900 | D2: Awa | E2: =COUNTIFS(sales!$D$2:$D$181, D2) -> 57 | F2: =AVERAGEIFS(sales!$H$2:$H$181, sales!$D$2:$D$181, D2) -> 10526.316
A3: Yopougon | B3: =SUMIFS(sales!$H$2:$H$181, sales!$C$2:$C$181, A3) -> 426500 | D3: Koffi | E3: =COUNTIFS(sales!$D$2:$D$181, D3) -> 46 | F3: =AVERAGEIFS(sales!$H$2:$H$181, sales!$D$2:$D$181, D3) -> 10915.217
A4: Marcory | B4: =SUMIFS(sales!$H$2:$H$181, sales!$C$2:$C$181, A4) -> 528600 | D4: Mariam | E4: =COUNTIFS(sales!$D$2:$D$181, D4) -> 41 | F4: =AVERAGEIFS(sales!$H$2:$H$181, sales!$D$2:$D$181, D4) -> 12553.659
A5: Plateau | B5: =SUMIFS(sales!$H$2:$H$181, sales!$C$2:$C$181, A5) -> 391100 | D5: Yao | E5: =COUNTIFS(sales!$D$2:$D$181, D5) -> 36 | F5: =AVERAGEIFS(sales!$H$2:$H$181, sales!$D$2:$D$181, D5) -> 14947.222
A6: Abobo | B6: =SUMIFS(sales!$H$2:$H$181, sales!$C$2:$C$181, A6) -> 383800
